LICENSE
MANIFEST.in
README.rst
setup.py
pyyama.egg-info/PKG-INFO
pyyama.egg-info/SOURCES.txt
pyyama.egg-info/dependency_links.txt
pyyama.egg-info/top_level.txt
yama/__init__.py
yama/__main__.py
yama/changeset.py
yama/core.py
yama/helpers.py
yama/versioning.py