Metadata-Version: 1.0
Name: pyyama
Version: 0.1.0
Summary: Python Toolkit for YAMA
Home-page: https://github.com/nishad/pyyama
Author: YAMA Project
Author-email: nish@n1sh.com
License: Copyright 2019 YAMA Project
